[
  {
    "t": "2026-03-11T12:00:00.000Z",
    "twl": 4.509,
    "tide": 4.276,
    "surge": 0.4,
    "src_time": "202603111200"
  },
  {
    "t": "2026-03-11T13:00:00.000Z",
    "twl": 3.709,
    "tide": 3.402,
    "surge": 0.4,
    "src_time": "202603111300"
  },
  {
    "t": "2026-03-11T14:00:00.000Z",
    "twl": 2.86,
    "tide": 2.443,
    "surge": 0.4,
    "src_time": "202603111400"
  },
  {
    "t": "2026-03-11T15:00:00.000Z",
    "twl": 2.049,
    "tide": 1.627,
    "surge": 0.4,
    "src_time": "202603111500"
  },
  {
    "t": "2026-03-11T16:00:00.000Z",
    "twl": 1.338,
    "tide": 1.03,
    "surge": 0.4,
    "src_time": "202603111600"
  },
  {
    "t": "2026-03-11T17:00:00.000Z",
    "twl": 0.918,
    "tide": 0.622,
    "surge": 0.4,
    "src_time": "202603111700"
  },
  {
    "t": "2026-03-11T18:00:00.000Z",
    "twl": 1.128,
    "tide": 0.672,
    "surge": 0.4,
    "src_time": "202603111800"
  },
  {
    "t": "2026-03-11T19:00:00.000Z",
    "twl": 2.318,
    "tide": 1.529,
    "surge": 0.4,
    "src_time": "202603111900"
  },
  {
    "t": "2026-03-11T20:00:00.000Z",
    "twl": 3.417,
    "tide": 2.729,
    "surge": 0.5,
    "src_time": "202603112000"
  },
  {
    "t": "2026-03-11T21:00:00.000Z",
    "twl": 4.218,
    "tide": 3.59,
    "surge": 0.5,
    "src_time": "202603112100"
  },
  {
    "t": "2026-03-11T22:00:00.000Z",
    "twl": 4.729,
    "tide": 4.112,
    "surge": 0.5,
    "src_time": "202603112200"
  },
  {
    "t": "2026-03-11T23:00:00.000Z",
    "twl": 4.657,
    "tide": 4.305,
    "surge": 0.5,
    "src_time": "202603112300"
  },
  {
    "t": "2026-03-12T00:00:00.000Z",
    "twl": 4.057,
    "tide": 4.032,
    "surge": 0.5,
    "src_time": "202603120000"
  },
  {
    "t": "2026-03-12T01:00:00.000Z",
    "twl": 3.339,
    "tide": 3.328,
    "surge": 0.6,
    "src_time": "202603120100"
  },
  {
    "t": "2026-03-12T02:00:00.000Z",
    "twl": 2.738,
    "tide": 2.392,
    "surge": 0.6,
    "src_time": "202603120200"
  },
  {
    "t": "2026-03-12T03:00:00.000Z",
    "twl": 2.099,
    "tide": 1.502,
    "surge": 0.6,
    "src_time": "202603120300"
  },
  {
    "t": "2026-03-12T04:00:00.000Z",
    "twl": 1.439,
    "tide": 0.892,
    "surge": 0.6,
    "src_time": "202603120400"
  },
  {
    "t": "2026-03-12T05:00:00.000Z",
    "twl": 1.279,
    "tide": 0.6,
    "surge": 0.6,
    "src_time": "202603120500"
  },
  {
    "t": "2026-03-12T06:00:00.000Z",
    "twl": 1.689,
    "tide": 0.728,
    "surge": 0.6,
    "src_time": "202603120600"
  },
  {
    "t": "2026-03-12T07:00:00.000Z",
    "twl": 2.768,
    "tide": 1.616,
    "surge": 0.6,
    "src_time": "202603120700"
  },
  {
    "t": "2026-03-12T08:00:00.000Z",
    "twl": 3.798,
    "tide": 3.026,
    "surge": 0.5,
    "src_time": "202603120800"
  },
  {
    "t": "2026-03-12T09:00:00.000Z",
    "twl": 4.759,
    "tide": 4.105,
    "surge": 0.5,
    "src_time": "202603120900"
  },
  {
    "t": "2026-03-12T10:00:00.000Z",
    "twl": 5.398,
    "tide": 4.674,
    "surge": 0.4,
    "src_time": "202603121000"
  },
  {
    "t": "2026-03-12T11:00:00.000Z",
    "twl": 5.648,
    "tide": 4.907,
    "surge": 0.4,
    "src_time": "202603121100"
  },
  {
    "t": "2026-03-12T12:00:00.000Z",
    "twl": 5.369,
    "tide": 4.758,
    "surge": 0.3,
    "src_time": "202603121200"
  },
  {
    "t": "2026-03-12T13:00:00.000Z",
    "twl": 4.618,
    "tide": 4.192,
    "surge": 0.2,
    "src_time": "202603121300"
  },
  {
    "t": "2026-03-12T14:00:00.000Z",
    "twl": 3.519,
    "tide": 3.343,
    "surge": 0.1,
    "src_time": "202603121400"
  },
  {
    "t": "2026-03-12T15:00:00.000Z",
    "twl": 2.528,
    "tide": 2.429,
    "surge": 0,
    "src_time": "202603121500"
  },
  {
    "t": "2026-03-12T16:00:00.000Z",
    "twl": 1.63,
    "tide": 1.654,
    "surge": -0.1,
    "src_time": "202603121600"
  },
  {
    "t": "2026-03-12T17:00:00.000Z",
    "twl": 0.81,
    "tide": 1.058,
    "surge": -0.2,
    "src_time": "202603121700"
  },
  {
    "t": "2026-03-12T18:00:00.000Z",
    "twl": 0.229,
    "tide": 0.64,
    "surge": -0.3,
    "src_time": "202603121800"
  },
  {
    "t": "2026-03-12T19:00:00.000Z",
    "twl": -0.088,
    "tide": 0.732,
    "surge": -0.4,
    "src_time": "202603121900"
  },
  {
    "t": "2026-03-12T20:00:00.000Z",
    "twl": 0.239,
    "tide": 1.626,
    "surge": -0.4,
    "src_time": "202603122000"
  },
  {
    "t": "2026-03-12T21:00:00.000Z",
    "twl": 1.328,
    "tide": 2.765,
    "surge": -0.5,
    "src_time": "202603122100"
  },
  {
    "t": "2026-03-12T22:00:00.000Z",
    "twl": 2.538,
    "tide": 3.573,
    "surge": -0.5,
    "src_time": "202603122200"
  },
  {
    "t": "2026-03-12T23:00:00.000Z",
    "twl": 3.46,
    "tide": 4.096,
    "surge": -0.5,
    "src_time": "202603122300"
  },
  {
    "t": "2026-03-13T00:00:00.000Z",
    "twl": 3.939,
    "tide": 4.286,
    "surge": -0.2,
    "src_time": "202603130000"
  },
  {
    "t": "2026-03-13T01:00:00.000Z",
    "twl": 3.689,
    "tide": 3.996,
    "surge": -0.1,
    "src_time": "202603130100"
  },
  {
    "t": "2026-03-13T02:00:00.000Z",
    "twl": 3.23,
    "tide": 3.284,
    "surge": -0.1,
    "src_time": "202603130200"
  },
  {
    "t": "2026-03-13T03:00:00.000Z",
    "twl": 2.558,
    "tide": 2.361,
    "surge": 0,
    "src_time": "202603130300"
  },
  {
    "t": "2026-03-13T04:00:00.000Z",
    "twl": 2.118,
    "tide": 1.5,
    "surge": 0,
    "src_time": "202603130400"
  },
  {
    "t": "2026-03-13T05:00:00.000Z",
    "twl": 1.669,
    "tide": 0.905,
    "surge": 0,
    "src_time": "202603130500"
  },
  {
    "t": "2026-03-13T06:00:00.000Z",
    "twl": 1.118,
    "tide": 0.6,
    "surge": 0,
    "src_time": "202603130600"
  },
  {
    "t": "2026-03-13T07:00:00.000Z",
    "twl": 1.02,
    "tide": 0.749,
    "surge": 0,
    "src_time": "202603130700"
  },
  {
    "t": "2026-03-13T08:00:00.000Z",
    "twl": 1.699,
    "tide": 1.695,
    "surge": 0,
    "src_time": "202603130800"
  },
  {
    "t": "2026-03-13T09:00:00.000Z",
    "twl": 2.807,
    "tide": 3.078,
    "surge": 0,
    "src_time": "202603130900"
  },
  {
    "t": "2026-03-13T10:00:00.000Z",
    "twl": 3.939,
    "tide": 4.091,
    "surge": 0,
    "src_time": "202603131000"
  },
  {
    "t": "2026-03-13T11:00:00.000Z",
    "twl": 4.719,
    "tide": 4.656,
    "surge": 0,
    "src_time": "202603131100"
  },
  {
    "t": "2026-03-13T12:00:00.000Z",
    "twl": 5.047,
    "tide": 4.908,
    "surge": 0.1,
    "src_time": "202603131200"
  },
  {
    "t": "2026-03-13T13:00:00.000Z",
    "twl": 4.877,
    "tide": 4.756,
    "surge": 0.1,
    "src_time": "202603131300"
  },
  {
    "t": "2026-03-13T14:00:00.000Z",
    "twl": 4.027,
    "tide": 4.184,
    "surge": 0.2,
    "src_time": "202603131400"
  },
  {
    "t": "2026-03-13T15:00:00.000Z",
    "twl": 3.25,
    "tide": 3.338,
    "surge": 0.2,
    "src_time": "202603131500"
  },
  {
    "t": "2026-03-13T16:00:00.000Z",
    "twl": 2.558,
    "tide": 2.436,
    "surge": 0.2,
    "src_time": "202603131600"
  },
  {
    "t": "2026-03-13T17:00:00.000Z",
    "twl": 1.8,
    "tide": 1.661,
    "surge": 0.3,
    "src_time": "202603131700"
  },
  {
    "t": "2026-03-13T18:00:00.000Z",
    "twl": 1.279,
    "tide": 1.028,
    "surge": 0.3,
    "src_time": "202603131800"
  },
  {
    "t": "2026-03-13T19:00:00.000Z",
    "twl": 0.97,
    "tide": 0.584,
    "surge": 0.3,
    "src_time": "202603131900"
  },
  {
    "t": "2026-03-13T20:00:00.000Z",
    "twl": 1.2,
    "tide": 0.728,
    "surge": 0.4,
    "src_time": "202603132000"
  },
  {
    "t": "2026-03-13T21:00:00.000Z",
    "twl": 2.479,
    "tide": 1.68,
    "surge": 0.5,
    "src_time": "202603132100"
  },
  {
    "t": "2026-03-13T22:00:00.000Z",
    "twl": 3.66,
    "tide": 2.807,
    "surge": 0.6,
    "src_time": "202603132200"
  },
  {
    "t": "2026-03-13T23:00:00.000Z",
    "twl": 4.7,
    "tide": 3.624,
    "surge": 0.7,
    "src_time": "202603132300"
  },
  {
    "t": "2026-03-14T00:00:00.000Z",
    "twl": 5.329,
    "tide": 4.181,
    "surge": 0.6,
    "src_time": "202603140000"
  },
  {
    "t": "2026-03-14T01:00:00.000Z",
    "twl": 5.297,
    "tide": 4.363,
    "surge": 0.6,
    "src_time": "202603140100"
  },
  {
    "t": "2026-03-14T02:00:00.000Z",
    "twl": 4.847,
    "tide": 4.033,
    "surge": 0.6,
    "src_time": "202603140200"
  },
  {
    "t": "2026-03-14T03:00:00.000Z",
    "twl": 3.978,
    "tide": 3.283,
    "surge": 0.6,
    "src_time": "202603140300"
  },
  {
    "t": "2026-03-14T04:00:00.000Z",
    "twl": 3.158,
    "tide": 2.339,
    "surge": 0.6,
    "src_time": "202603140400"
  },
  {
    "t": "2026-03-14T05:00:00.000Z",
    "twl": 2.387,
    "tide": 1.474,
    "surge": 0.6,
    "src_time": "202603140500"
  },
  {
    "t": "2026-03-14T06:00:00.000Z",
    "twl": 1.699,
    "tide": 0.857,
    "surge": 0.6,
    "src_time": "202603140600"
  },
  {
    "t": "2026-03-14T07:00:00.000Z",
    "twl": 1.02,
    "tide": 0.514,
    "surge": 0.5,
    "src_time": "202603140700"
  },
  {
    "t": "2026-03-14T08:00:00.000Z",
    "twl": 0.59,
    "tide": 0.682,
    "surge": 0.4,
    "src_time": "202603140800"
  },
  {
    "t": "2026-03-14T09:00:00.000Z",
    "twl": 1.781,
    "tide": 1.696,
    "surge": 0.3,
    "src_time": "202603140900"
  },
  {
    "t": "2026-03-14T10:00:00.000Z",
    "twl": 3.289,
    "tide": 3.09,
    "surge": 0.2,
    "src_time": "202603141000"
  },
  {
    "t": "2026-03-14T11:00:00.000Z",
    "twl": 4.48,
    "tide": 4.105,
    "surge": 0.1,
    "src_time": "202603141100"
  },
  {
    "t": "2026-03-14T12:00:00.000Z",
    "twl": 5.359,
    "tide": 4.716,
    "surge": 0.1,
    "src_time": "202603141200"
  },
  {
    "t": "2026-03-14T13:00:00.000Z",
    "twl": 5.657,
    "tide": 4.993,
    "surge": 0.1,
    "src_time": "202603141300"
  },
  {
    "t": "2026-03-14T14:00:00.000Z",
    "twl": 5.307,
    "tide": 4.819,
    "surge": 0,
    "src_time": "202603141400"
  },
  {
    "t": "2026-03-14T15:00:00.000Z",
    "twl": 4.267,
    "tide": 4.206,
    "surge": 0,
    "src_time": "202603141500"
  },
  {
    "t": "2026-03-14T16:00:00.000Z",
    "twl": 3.178,
    "tide": 3.326,
    "surge": 0,
    "src_time": "202603141600"
  },
  {
    "t": "2026-03-14T17:00:00.000Z",
    "twl": 2.4,
    "tide": 2.403,
    "surge": -0.1,
    "src_time": "202603141700"
  },
  {
    "t": "2026-03-14T18:00:00.000Z",
    "twl": 1.61,
    "tide": 1.599,
    "surge": -0.1,
    "src_time": "202603141800"
  },
  {
    "t": "2026-03-14T19:00:00.000Z",
    "twl": 0.819,
    "tide": 0.914,
    "surge": -0.1,
    "src_time": "202603141900"
  },
  {
    "t": "2026-03-14T20:00:00.000Z",
    "twl": 0.219,
    "tide": 0.46,
    "surge": -0.2,
    "src_time": "202603142000"
  },
  {
    "t": "2026-03-14T21:00:00.000Z",
    "twl": -0.059,
    "tide": 0.697,
    "surge": -0.3,
    "src_time": "202603142100"
  },
  {
    "t": "2026-03-14T22:00:00.000Z",
    "twl": 0.619,
    "tide": 1.755,
    "surge": -0.3,
    "src_time": "202603142200"
  },
  {
    "t": "2026-03-14T23:00:00.000Z",
    "twl": 1.958,
    "tide": 2.926,
    "surge": -0.3,
    "src_time": "202603142300"
  },
  {
    "t": "2026-03-15T00:00:00.000Z",
    "twl": 3.007,
    "tide": 3.793,
    "surge": -0.2,
    "src_time": "202603150000"
  },
  {
    "t": "2026-03-15T01:00:00.000Z",
    "twl": 3.768,
    "tide": 4.375,
    "surge": -0.2,
    "src_time": "202603150100"
  },
  {
    "t": "2026-03-15T02:00:00.000Z",
    "twl": 4.099,
    "tide": 4.509,
    "surge": -0.2,
    "src_time": "202603150200"
  },
  {
    "t": "2026-03-15T03:00:00.000Z",
    "twl": 3.65,
    "tide": 4.097,
    "surge": -0.1,
    "src_time": "202603150300"
  },
  {
    "t": "2026-03-15T04:00:00.000Z",
    "twl": 2.807,
    "tide": 3.271,
    "surge": -0.1,
    "src_time": "202603150400"
  },
  {
    "t": "2026-03-15T05:00:00.000Z",
    "twl": 1.967,
    "tide": 2.28,
    "surge": -0.1,
    "src_time": "202603150500"
  },
  {
    "t": "2026-03-15T06:00:00.000Z",
    "twl": 1.17,
    "tide": 1.39,
    "surge": -0.2,
    "src_time": "202603150600"
  },
  {
    "t": "2026-03-15T07:00:00.000Z",
    "twl": 0.409,
    "tide": 0.734,
    "surge": -0.2,
    "src_time": "202603150700"
  },
  {
    "t": "2026-03-15T08:00:00.000Z",
    "twl": -0.19,
    "tide": 0.351,
    "surge": -0.2,
    "src_time": "202603150800"
  },
  {
    "t": "2026-03-15T09:00:00.000Z",
    "twl": 0.029,
    "tide": 0.565,
    "surge": -0.2,
    "src_time": "202603150900"
  },
  {
    "t": "2026-03-15T10:00:00.000Z",
    "twl": 1.548,
    "tide": 1.688,
    "surge": -0.2,
    "src_time": "202603151000"
  },
  {
    "t": "2026-03-15T11:00:00.000Z",
    "twl": 2.919,
    "tide": 3.14,
    "surge": -0.2,
    "src_time": "202603151100"
  },
  {
    "t": "2026-03-15T12:00:00.000Z",
    "twl": 4.267,
    "tide": 4.203,
    "surge": -0.2,
    "src_time": "202603151200"
  },
  {
    "t": "2026-03-15T13:00:00.000Z",
    "twl": 5.359,
    "tide": 4.867,
    "surge": -0.2,
    "src_time": "202603151300"
  },
  {
    "t": "2026-03-15T14:00:00.000Z",
    "twl": 5.867,
    "tide": 5.134,
    "surge": -0.2,
    "src_time": "202603151400"
  },
  {
    "t": "2026-03-15T15:00:00.000Z",
    "twl": 5.73,
    "tide": 4.889,
    "surge": -0.1,
    "src_time": "202603151500"
  },
  {
    "t": "2026-03-15T16:00:00.000Z",
    "twl": 4.959,
    "tide": 4.193,
    "surge": -0.1,
    "src_time": "202603151600"
  },
  {
    "t": "2026-03-15T17:00:00.000Z",
    "twl": 4.119,
    "tide": 3.249,
    "surge": 0,
    "src_time": "202603151700"
  },
  {
    "t": "2026-03-15T18:00:00.000Z",
    "twl": 3.138,
    "tide": 2.286,
    "surge": 0.1,
    "src_time": "202603151800"
  },
  {
    "t": "2026-03-15T19:00:00.000Z",
    "twl": 2.328,
    "tide": 1.444,
    "surge": 0.2,
    "src_time": "202603151900"
  },
  {
    "t": "2026-03-15T20:00:00.000Z",
    "twl": 1.528,
    "tide": 0.717,
    "surge": 0.2,
    "src_time": "202603152000"
  },
  {
    "t": "2026-03-15T21:00:00.000Z",
    "twl": 0.888,
    "tide": 0.3,
    "surge": 0.3,
    "src_time": "202603152100"
  },
  {
    "t": "2026-03-15T22:00:00.000Z",
    "twl": 1.059,
    "tide": 0.702,
    "surge": 0.3,
    "src_time": "202603152200"
  },
  {
    "t": "2026-03-15T23:00:00.000Z",
    "twl": 2.469,
    "tide": 1.927,
    "surge": 0.4,
    "src_time": "202603152300"
  },
  {
    "t": "2026-03-16T00:00:00.000Z",
    "twl": 3.798,
    "tide": 3.18,
    "surge": 0.5,
    "src_time": "202603160000"
  },
  {
    "t": "2026-03-16T01:00:00.000Z",
    "twl": 4.637,
    "tide": 4.095,
    "surge": 0.5,
    "src_time": "202603160100"
  },
  {
    "t": "2026-03-16T02:00:00.000Z",
    "twl": 5.549,
    "tide": 4.651,
    "surge": 0.6,
    "src_time": "202603160200"
  },
  {
    "t": "2026-03-16T03:00:00.000Z",
    "twl": 5.628,
    "tide": 4.676,
    "surge": 0.6,
    "src_time": "202603160300"
  },
  {
    "t": "2026-03-16T04:00:00.000Z",
    "twl": 5.218,
    "tide": 4.135,
    "surge": 0.7,
    "src_time": "202603160400"
  },
  {
    "t": "2026-03-16T05:00:00.000Z",
    "twl": 4.247,
    "tide": 3.207,
    "surge": 0.8,
    "src_time": "202603160500"
  },
  {
    "t": "2026-03-16T06:00:00.000Z",
    "twl": 3.417,
    "tide": 2.159,
    "surge": 0.9,
    "src_time": "202603160600"
  },
  {
    "t": "2026-03-16T07:00:00.000Z",
    "twl": 2.587,
    "tide": 1.24,
    "surge": 1,
    "src_time": "202603160700"
  },
  {
    "t": "2026-03-16T08:00:00.000Z",
    "twl": 1.908,
    "tide": 0.544,
    "surge": 1,
    "src_time": "202603160800"
  },
  {
    "t": "2026-03-16T09:00:00.000Z",
    "twl": 1.708,
    "tide": 0.145,
    "surge": 1.1,
    "src_time": "202603160900"
  },
  {
    "t": "2026-03-16T10:00:00.000Z",
    "twl": 2.469,
    "tide": 0.459,
    "surge": 1.2,
    "src_time": "202603161000"
  },
  {
    "t": "2026-03-16T11:00:00.000Z",
    "twl": 3.637,
    "tide": 1.743,
    "surge": 1.2,
    "src_time": "202603161100"
  },
  {
    "t": "2026-03-16T12:00:00.000Z",
    "twl": 4.828,
    "tide": 3.286,
    "surge": 1.2,
    "src_time": "202603161200"
  },
  {
    "t": "2026-03-16T13:00:00.000Z",
    "twl": 5.828,
    "tide": 4.402,
    "surge": 1.2,
    "src_time": "202603161300"
  },
  {
    "t": "2026-03-16T14:00:00.000Z",
    "twl": 6.458,
    "tide": 5.079,
    "surge": 1.2,
    "src_time": "202603161400"
  },
  {
    "t": "2026-03-16T15:00:00.000Z",
    "twl": 6.697,
    "tide": 5.27,
    "surge": 1.2,
    "src_time": "202603161500"
  },
  {
    "t": "2026-03-16T16:00:00.000Z",
    "twl": 6.487,
    "tide": 4.9,
    "surge": 1.2,
    "src_time": "202603161600"
  },
  {
    "t": "2026-03-16T17:00:00.000Z",
    "twl": 5.707,
    "tide": 4.09,
    "surge": 1.2,
    "src_time": "202603161700"
  },
  {
    "t": "2026-03-16T18:00:00.000Z",
    "twl": 4.658,
    "tide": 3.068,
    "surge": 1.2,
    "src_time": "202603161800"
  },
  {
    "t": "2026-03-16T19:00:00.000Z",
    "twl": 3.73,
    "tide": 2.066,
    "surge": 1.3,
    "src_time": "202603161900"
  },
  {
    "t": "2026-03-16T20:00:00.000Z",
    "twl": 2.834,
    "tide": 1.197,
    "surge": 1.3,
    "src_time": "202603162000"
  },
  {
    "t": "2026-03-16T21:00:00.000Z",
    "twl": 2.075,
    "tide": 0.465,
    "surge": 1.3,
    "src_time": "202603162100"
  },
  {
    "t": "2026-03-16T22:00:00.000Z",
    "twl": 1.844,
    "tide": 0.16,
    "surge": 1.4,
    "src_time": "202603162200"
  },
  {
    "t": "2026-03-16T23:00:00.000Z",
    "twl": 2.472,
    "tide": 0.815,
    "surge": 1.4,
    "src_time": "202603162300"
  },
  {
    "t": "2026-03-17T00:00:00.000Z",
    "twl": 3.982,
    "tide": 2.252,
    "surge": 1.5,
    "src_time": "202603170000"
  },
  {
    "t": "2026-03-17T01:00:00.000Z",
    "twl": 5.292,
    "tide": 3.588,
    "surge": 1.5,
    "src_time": "202603170100"
  },
  {
    "t": "2026-03-17T02:00:00.000Z",
    "twl": 6.178,
    "tide": 4.501,
    "surge": 1.5,
    "src_time": "202603170200"
  },
  {
    "t": "2026-03-17T03:00:00.000Z",
    "twl": 6.605,
    "tide": 4.954,
    "surge": 1.5,
    "src_time": "202603170300"
  },
  {
    "t": "2026-03-17T04:00:00.000Z",
    "twl": 6.333,
    "tide": 4.809,
    "surge": 1.4,
    "src_time": "202603170400"
  },
  {
    "t": "2026-03-17T05:00:00.000Z",
    "twl": 5.406,
    "tide": 4.109,
    "surge": 1.2,
    "src_time": "202603170500"
  },
  {
    "t": "2026-03-17T06:00:00.000Z",
    "twl": 4.271,
    "tide": 3.074,
    "surge": 1.1,
    "src_time": "202603170600"
  },
  {
    "t": "2026-03-17T07:00:00.000Z",
    "twl": 2.873,
    "tide": 1.976,
    "surge": 0.8,
    "src_time": "202603170700"
  },
  {
    "t": "2026-03-17T08:00:00.000Z",
    "twl": 1.634,
    "tide": 1.037,
    "surge": 0.5,
    "src_time": "202603170800"
  },
  {
    "t": "2026-03-17T09:00:00.000Z",
    "twl": 0.613,
    "tide": 0.316,
    "surge": 0.2,
    "src_time": "202603170900"
  },
  {
    "t": "2026-03-17T10:00:00.000Z",
    "twl": -0.155,
    "tide": -0.052,
    "surge": -0.2,
    "src_time": "202603171000"
  },
  {
    "t": "2026-03-17T11:00:00.000Z",
    "twl": 0.025,
    "tide": 0.428,
    "surge": -0.5,
    "src_time": "202603171100"
  },
  {
    "t": "2026-03-17T12:00:00.000Z",
    "twl": 1.212,
    "tide": 1.915,
    "surge": -0.8,
    "src_time": "202603171200"
  },
  {
    "t": "2026-03-17T13:00:00.000Z",
    "twl": 2.643,
    "tide": 3.546,
    "surge": -1,
    "src_time": "202603171300"
  },
  {
    "t": "2026-03-17T14:00:00.000Z",
    "twl": 3.671,
    "tide": 4.674,
    "surge": -1.1,
    "src_time": "202603171400"
  },
  {
    "t": "2026-03-17T15:00:00.000Z",
    "twl": 4.286,
    "tide": 5.289,
    "surge": -1.1,
    "src_time": "202603171500"
  },
  {
    "t": "2026-03-17T16:00:00.000Z",
    "twl": 4.434,
    "tide": 5.337,
    "surge": -1,
    "src_time": "202603171600"
  },
  {
    "t": "2026-03-17T17:00:00.000Z",
    "twl": 3.902,
    "tide": 4.805,
    "surge": -1,
    "src_time": "202603171700"
  },
  {
    "t": "2026-03-17T18:00:00.000Z",
    "twl": 3.067,
    "tide": 3.87,
    "surge": -0.9,
    "src_time": "202603171800"
  },
  {
    "t": "2026-03-17T19:00:00.000Z",
    "twl": 1.975,
    "tide": 2.778,
    "surge": -0.9,
    "src_time": "202603171900"
  },
  {
    "t": "2026-03-17T20:00:00.000Z",
    "twl": 0.952,
    "tide": 1.755,
    "surge": -0.9,
    "src_time": "202603172000"
  },
  {
    "t": "2026-03-17T21:00:00.000Z",
    "twl": 0.084,
    "tide": 0.887,
    "surge": -0.9,
    "src_time": "202603172100"
  },
  {
    "t": "2026-03-17T22:00:00.000Z",
    "twl": -0.594,
    "tide": 0.209,
    "surge": -0.9,
    "src_time": "202603172200"
  },
  {
    "t": "2026-03-17T23:00:00.000Z",
    "twl": -0.594,
    "tide": 0.109,
    "surge": -0.8,
    "src_time": "202603172300"
  },
  {
    "t": "2026-03-18T00:00:00.000Z",
    "twl": 0.392,
    "tide": 1.095,
    "surge": -0.8,
    "src_time": "202603180000"
  },
  {
    "t": "2026-03-18T01:00:00.000Z",
    "twl": 2.144,
    "tide": 2.747,
    "surge": -0.7,
    "src_time": "202603180100"
  },
  {
    "t": "2026-03-18T02:00:00.000Z",
    "twl": 3.51,
    "tide": 4.113,
    "surge": -0.7,
    "src_time": "202603180200"
  },
  {
    "t": "2026-03-18T03:00:00.000Z",
    "twl": 4.343,
    "tide": 4.946,
    "surge": -0.7,
    "src_time": "202603180300"
  },
  {
    "t": "2026-03-18T04:00:00.000Z",
    "twl": 4.618,
    "tide": 5.221,
    "surge": -0.7,
    "src_time": "202603180400"
  },
  {
    "t": "2026-03-18T05:00:00.000Z",
    "twl": 4.167,
    "tide": 4.87,
    "surge": -0.8,
    "src_time": "202603180500"
  },
  {
    "t": "2026-03-18T06:00:00.000Z",
    "twl": 3.303,
    "tide": 4.006,
    "surge": -0.8,
    "src_time": "202603180600"
  },
  {
    "t": "2026-03-18T07:00:00.000Z",
    "twl": 2.174,
    "tide": 2.877,
    "surge": -0.8,
    "src_time": "202603180700"
  },
  {
    "t": "2026-03-18T08:00:00.000Z",
    "twl": 1.047,
    "tide": 1.75,
    "surge": -0.8,
    "src_time": "202603180800"
  },
  {
    "t": "2026-03-18T09:00:00.000Z",
    "twl": 0.106,
    "tide": 0.809,
    "surge": -0.8,
    "src_time": "202603180900"
  },
  {
    "t": "2026-03-18T10:00:00.000Z",
    "twl": -0.712,
    "tide": 0.091,
    "surge": -0.9,
    "src_time": "202603181000"
  },
  {
    "t": "2026-03-18T11:00:00.000Z",
    "twl": -0.893,
    "tide": -0.19,
    "surge": -0.8,
    "src_time": "202603181100"
  },
  {
    "t": "2026-03-18T12:00:00.000Z",
    "twl": -0.182,
    "tide": 0.521,
    "surge": -0.8,
    "src_time": "202603181200"
  },
  {
    "t": "2026-03-18T13:00:00.000Z",
    "twl": 1.514,
    "tide": 2.217,
    "surge": -0.8,
    "src_time": "202603181300"
  },
  {
    "t": "2026-03-18T14:00:00.000Z",
    "twl": 3.281,
    "tide": 3.884,
    "surge": -0.7,
    "src_time": "202603181400"
  },
  {
    "t": "2026-03-18T15:00:00.000Z",
    "twl": 4.447,
    "tide": 4.95,
    "surge": -0.6,
    "src_time": "202603181500"
  },
  {
    "t": "2026-03-18T16:00:00.000Z",
    "twl": 4.927,
    "tide": 5.43,
    "surge": -0.6,
    "src_time": "202603181600"
  },
  {
    "t": "2026-03-18T17:00:00.000Z",
    "twl": 4.888,
    "tide": 5.291,
    "surge": -0.5,
    "src_time": "202603181700"
  },
  {
    "t": "2026-03-18T18:00:00.000Z",
    "twl": 4.187,
    "tide": 4.59,
    "surge": -0.5,
    "src_time": "202603181800"
  },
  {
    "t": "2026-03-18T19:00:00.000Z",
    "twl": 3.239,
    "tide": 3.542,
    "surge": -0.4,
    "src_time": "202603181900"
  },
  {
    "t": "2026-03-18T20:00:00.000Z",
    "twl": 2.102,
    "tide": 2.405,
    "surge": -0.4,
    "src_time": "202603182000"
  },
  {
    "t": "2026-03-18T21:00:00.000Z",
    "twl": 1.187,
    "tide": 1.39,
    "surge": -0.3,
    "src_time": "202603182100"
  },
  {
    "t": "2026-03-18T22:00:00.000Z",
    "twl": 0.461,
    "tide": 0.564,
    "surge": -0.2,
    "src_time": "202603182200"
  },
  {
    "t": "2026-03-18T23:00:00.000Z",
    "twl": 0.009,
    "tide": 0.012,
    "surge": -0.1,
    "src_time": "202603182300"
  },
  {
    "t": "2026-03-19T00:00:00.000Z",
    "twl": 0.206,
    "tide": 0.209,
    "surge": -0.1,
    "src_time": "202603190000"
  },
  {
    "t": "2026-03-19T01:00:00.000Z",
    "twl": 1.659,
    "tide": 1.562,
    "surge": 0,
    "src_time": "202603190100"
  },
  {
    "t": "2026-03-19T02:00:00.000Z",
    "twl": 3.465,
    "tide": 3.368,
    "surge": 0,
    "src_time": "202603190200"
  },
  {
    "t": "2026-03-19T03:00:00.000Z",
    "twl": 4.774,
    "tide": 4.677,
    "surge": 0,
    "src_time": "202603190300"
  },
  {
    "t": "2026-03-19T04:00:00.000Z",
    "twl": 5.448,
    "tide": 5.351,
    "surge": 0,
    "src_time": "202603190400"
  },
  {
    "t": "2026-03-19T05:00:00.000Z",
    "twl": 5.604,
    "tide": 5.407,
    "surge": 0.1,
    "src_time": "202603190500"
  },
  {
    "t": "2026-03-19T06:00:00.000Z",
    "twl": 5.042,
    "tide": 4.845,
    "surge": 0.1,
    "src_time": "202603190600"
  },
  {
    "t": "2026-03-19T07:00:00.000Z",
    "twl": 4.033,
    "tide": 3.836,
    "surge": 0.1,
    "src_time": "202603190700"
  },
  {
    "t": "2026-03-19T08:00:00.000Z",
    "twl": 2.838,
    "tide": 2.641,
    "surge": 0.1,
    "src_time": "202603190800"
  },
  {
    "t": "2026-03-19T09:00:00.000Z",
    "twl": 1.71,
    "tide": 1.513,
    "surge": 0.1,
    "src_time": "202603190900"
  },
  {
    "t": "2026-03-19T10:00:00.000Z",
    "twl": 0.79,
    "tide": 0.593,
    "surge": 0.1,
    "src_time": "202603191000"
  },
  {
    "t": "2026-03-19T11:00:00.000Z",
    "twl": 0.113,
    "tide": -0.084,
    "surge": 0.1,
    "src_time": "202603191100"
  },
  {
    "t": "2026-03-19T12:00:00.000Z",
    "twl": 0.077,
    "tide": -0.22,
    "surge": 0.2,
    "src_time": "202603191200"
  },
  {
    "t": "2026-03-19T13:00:00.000Z",
    "twl": 1.053,
    "tide": 0.756,
    "surge": 0.2,
    "src_time": "202603191300"
  },
  {
    "t": "2026-03-19T14:00:00.000Z",
    "twl": 2.909,
    "tide": 2.612,
    "surge": 0.2,
    "src_time": "202603191400"
  },
  {
    "t": "2026-03-19T15:00:00.000Z",
    "twl": 4.627,
    "tide": 4.23,
    "surge": 0.3,
    "src_time": "202603191500"
  },
  {
    "t": "2026-03-19T16:00:00.000Z",
    "twl": 5.558,
    "tide": 5.161,
    "surge": 0.3,
    "src_time": "202603191600"
  },
  {
    "t": "2026-03-19T17:00:00.000Z",
    "twl": 5.854,
    "tide": 5.457,
    "surge": 0.3,
    "src_time": "202603191700"
  },
  {
    "t": "2026-03-19T18:00:00.000Z",
    "twl": 5.522,
    "tide": 5.125,
    "surge": 0.3,
    "src_time": "202603191800"
  },
  {
    "t": "2026-03-19T19:00:00.000Z",
    "twl": 4.771,
    "tide": 4.274,
    "surge": 0.4,
    "src_time": "202603191900"
  },
  {
    "t": "2026-03-19T20:00:00.000Z",
    "twl": 3.642,
    "tide": 3.145,
    "surge": 0.4,
    "src_time": "202603192000"
  },
  {
    "t": "2026-03-19T21:00:00.000Z",
    "twl": 2.492,
    "tide": 1.995,
    "surge": 0.4,
    "src_time": "202603192100"
  },
  {
    "t": "2026-03-19T22:00:00.000Z",
    "twl": 1.522,
    "tide": 1.025,
    "surge": 0.4,
    "src_time": "202603192200"
  },
  {
    "t": "2026-03-19T23:00:00.000Z",
    "twl": 0.788,
    "tide": 0.291,
    "surge": 0.4,
    "src_time": "202603192300"
  },
  {
    "t": "2026-03-20T00:00:00.000Z",
    "twl": 0.432,
    "tide": -0.065,
    "surge": 0.4,
    "src_time": "202603200000"
  },
  {
    "t": "2026-03-20T01:00:00.000Z",
    "twl": 1.085,
    "tide": 0.488,
    "surge": 0.5,
    "src_time": "202603200100"
  },
  {
    "t": "2026-03-20T02:00:00.000Z",
    "twl": 2.771,
    "tide": 2.174,
    "surge": 0.5,
    "src_time": "202603200200"
  },
  {
    "t": "2026-03-20T03:00:00.000Z",
    "twl": 4.619,
    "tide": 4.022,
    "surge": 0.5,
    "src_time": "202603200300"
  },
  {
    "t": "2026-03-20T04:00:00.000Z",
    "twl": 5.784,
    "tide": 5.187,
    "surge": 0.5,
    "src_time": "202603200400"
  },
  {
    "t": "2026-03-20T05:00:00.000Z",
    "twl": 6.253,
    "tide": 5.656,
    "surge": 0.5,
    "src_time": "202603200500"
  },
  {
    "t": "2026-03-20T06:00:00.000Z",
    "twl": 6.085,
    "tide": 5.488,
    "surge": 0.5,
    "src_time": "202603200600"
  },
  {
    "t": "2026-03-20T07:00:00.000Z",
    "twl": 5.339,
    "tide": 4.742,
    "surge": 0.5,
    "src_time": "202603200700"
  },
  {
    "t": "2026-03-20T08:00:00.000Z",
    "twl": 4.223,
    "tide": 3.626,
    "surge": 0.5,
    "src_time": "202603200800"
  },
  {
    "t": "2026-03-20T09:00:00.000Z",
    "twl": 3,
    "tide": 2.403,
    "surge": 0.5,
    "src_time": "202603200900"
  },
  {
    "t": "2026-03-20T10:00:00.000Z",
    "twl": 1.901,
    "tide": 1.304,
    "surge": 0.5,
    "src_time": "202603201000"
  },
  {
    "t": "2026-03-20T11:00:00.000Z",
    "twl": 1.028,
    "tide": 0.431,
    "surge": 0.5,
    "src_time": "202603201100"
  },
  {
    "t": "2026-03-20T12:00:00.000Z",
    "twl": 0.428,
    "tide": -0.169,
    "surge": 0.5,
    "src_time": "202603201200"
  },
  {
    "t": "2026-03-20T13:00:00.000Z",
    "twl": 0.477,
    "tide": -0.12,
    "surge": 0.5,
    "src_time": "202603201300"
  },
  {
    "t": "2026-03-20T14:00:00.000Z",
    "twl": 1.702,
    "tide": 1.105,
    "surge": 0.5,
    "src_time": "202603201400"
  },
  {
    "t": "2026-03-20T15:00:00.000Z",
    "twl": 3.622,
    "tide": 3.025,
    "surge": 0.5,
    "src_time": "202603201500"
  },
  {
    "t": "2026-03-20T16:00:00.000Z",
    "twl": 5.103,
    "tide": 4.506,
    "surge": 0.5,
    "src_time": "202603201600"
  },
  {
    "t": "2026-03-20T17:00:00.000Z",
    "twl": 5.853,
    "tide": 5.256,
    "surge": 0.5,
    "src_time": "202603201700"
  },
  {
    "t": "2026-03-20T18:00:00.000Z",
    "twl": 5.962,
    "tide": 5.365,
    "surge": 0.5,
    "src_time": "202603201800"
  }
]
